ledsa/__init__.py
ledsa/__main__.py
ledsa/analysis/ConfigDataAnalysis.py
ledsa/analysis/Experiment.py
ledsa/analysis/ExperimentData.py
ledsa/analysis/ExtinctionCoefficients.py
ledsa/analysis/ExtinctionCoefficientsLinear.py
ledsa/analysis/ExtinctionCoefficientsNonLinear.py
ledsa/analysis/__init__.py
ledsa/analysis/data_preparation.py
ledsa/core/ConfigData.py
ledsa/core/__init__.py
ledsa/core/file_handling.py
ledsa/core/image_handling.py
ledsa/core/image_reading.py
ledsa/core/parser_arguments_declaration.py
ledsa/core/parser_arguments_run.py
ledsa/data_extraction/DataExtractor.py
ledsa/data_extraction/LEDAnalysisData.py
ledsa/data_extraction/__init__.py
ledsa/data_extraction/init_functions.py
ledsa/data_extraction/model.py
ledsa/data_extraction/step_1_functions.py
ledsa/data_extraction/step_2_functions.py
ledsa/data_extraction/step_3_functions.py
ledsa/demo/__init__.py
ledsa/demo/demo_run.py
ledsa/demo/demo_setup.py
ledsa/ledpositions/__init__.py
ledsa/ledpositions/coordinates.py
ledsa/postprocessing/__init__.py
ledsa/postprocessing/helper_functions.py
ledsa/postprocessing/simulation.py
ledsa/tests/__init__.py
ledsa/tests/__main__.py
ledsa/tests/AcceptanceTests/LedsaATestLibrary.py
ledsa/tests/AcceptanceTests/TestExperiment.py
ledsa/tests/AcceptanceTests/__init__.py
ledsa/tests/AcceptanceTests/__main__.py
ledsa/tools/__init__.py
ledsa/tools/photo_renamer.py
ledsa-0.9.5.dist-info/METADATA
ledsa-0.9.5.dist-info/WHEEL
ledsa-0.9.5.dist-info/top_level.txt
ledsa-0.9.5.dist-info/RECORD
