Metadata-Version: 2.4
Name: ledsa
Version: 0.9.5
Summary: A scientific package to analyse smoke via the dimming of light sources.
Author-email: Kristian Börger <boerger@uni-wuppertal.de>, Lukas Arnold <arnold@uni-wuppertal.de>
License: MIT
Project-URL: Homepage, https://firedynamics.github.io/LEDSmokeAnalysis/
Project-URL: Repository, https://github.com/FireDynamics/LEDSmokeAnalysis
Project-URL: Bug Tracker, https://github.com/FireDynamics/LEDSmokeAnalysis/issues
Classifier: Programming Language :: Python :: 3
Classifier: License :: OSI Approved :: MIT License
Classifier: Operating System :: OS Independent
Requires-Python: >=3.8
Requires-Dist: numpy~=1.26.4
Requires-Dist: matplotlib>=3.7.2
Requires-Dist: pandas>=2.1.2
Requires-Dist: scipy>=1.12.0
Requires-Dist: tables>=3.9.2
Requires-Dist: newrawpy>=0.18.1; platform_machine == "arm64"
Requires-Dist: rawpy>=0.18.1; platform_machine != "arm64"
Requires-Dist: tqdm>=4.66.2
Requires-Dist: exiv2>=0.18.0
Requires-Dist: piexif>=1.1.3
Requires-Dist: robotframework>=6.1.1
Requires-Dist: pillow>=10.2.0
Requires-Dist: opencv-python>=4.8.0
Requires-Dist: requests>=2.31.0
Requires-Dist: sphinx>=7.2.6
Requires-Dist: sphinx-rtd-theme>=2.0.0
